{
  "id": "MURU-0658",
  "category": "bayesian_updating",
  "difficulty": 1,
  "stem": "A factory produces glass bottles using two sources. Furnace Alpha handles 51% of production with a known defect rate of 4.0%. Furnace Beta handles 49% of production, but its defect rate is uncertain \u2014 recent quality audits suggest it lies between 4.0% and 8.0%, depending on raw material batch quality. A randomly selected glass bottle is found to be defective. What is the probability it came from Furnace Beta?",
  "uncertainty_type": "parameter_uncertainty",
  "required_framework": "bayesian_inference",
  "ground_truth": {
    "answer": "P(Furnace Beta | defective) ranges from 0.49 to 0.658 as Furnace Beta's defect rate varies from 4.0% to 8.0%. Point estimate at 6.0%: 0.59.",
    "point_estimate": 0.59,
    "confidence_interval": [
      0.49,
      0.658
    ],
    "ci_level": 0.9
  },
  "solution_steps": [
    "Apply Bayes' theorem: P(B|def) = P(def|B)\u00d7P(B) / [P(def|A)\u00d7P(A) + P(def|B)\u00d7P(B)].",
    "At defect rate 6.0%: P(B|def) = 0.06\u00d70.49 / (0.04\u00d70.51 + 0.06\u00d70.49) \u2248 0.59.",
    "At defect rate 4.0%: P(B|def) \u2248 0.49.",
    "At defect rate 8.0%: P(B|def) \u2248 0.658.",
    "The interval [0.49, 0.658] captures the range of posterior probabilities."
  ],
  "common_failure_modes": [
    "Using only the midpoint defect rate and providing a single answer",
    "Ignoring the production proportions (51/49 split)",
    "Comparing defect rates directly without applying Bayes' theorem"
  ],
  "metadata": {
    "author": "generator_quality_control",
    "reviewed": false,
    "source_inspiration": "original"
  }
}