{
  "id": "MURU-2080",
  "category": "bayesian_updating",
  "difficulty": 5,
  "stem": "In a clinical trial scenario, a researcher begins with a prior probability of 57% that the drug is effective, based on patient outcomes. After batch of patients 1, contradicting evidence arrives with a likelihood ratio estimated between 0.44 and 0.6. After batch of patients 2, supporting evidence arrives with a likelihood ratio estimated between 2.15 and 2.8. After batch of patients 3, supporting evidence arrives with a likelihood ratio estimated between 1.6 and 2.63. After batch of patients 4, contradicting evidence arrives with a likelihood ratio estimated between 0.31 and 0.42. After batch of patients 5, contradicting evidence arrives with a likelihood ratio estimated between 0.45 and 0.73. What is the posterior probability that the drug is effective after all 5 observations, accounting for the uncertainty in each likelihood ratio?",
  "uncertainty_type": "parameter_uncertainty",
  "required_framework": "bayesian_inference",
  "ground_truth": {
    "answer": "After 5 sequential Bayesian updates, P(the drug is effective) ranges from 0.219 to 0.642. Point estimate: 0.434.",
    "point_estimate": 0.434,
    "confidence_interval": [
      0.219,
      0.642
    ],
    "ci_level": 0.9
  },
  "solution_steps": [
    "Start with prior odds = 0.57/0.43 = 1.326.",
    "Update 1: multiply odds by LR \u2208 [0.44, 0.6] (mid: 0.52, contradicting evidence).",
    "Update 2: multiply odds by LR \u2208 [2.15, 2.8] (mid: 2.47, supporting evidence).",
    "Update 3: multiply odds by LR \u2208 [1.6, 2.63] (mid: 2.12, supporting evidence).",
    "Update 4: multiply odds by LR \u2208 [0.31, 0.42] (mid: 0.36, contradicting evidence).",
    "Update 5: multiply odds by LR \u2208 [0.45, 0.73] (mid: 0.59, contradicting evidence).",
    "Convert final odds back to probability: P = odds/(1+odds). Range: [0.219, 0.642], point estimate: 0.434."
  ],
  "common_failure_modes": [
    "Treating each update independently instead of applying them sequentially to the running posterior",
    "Using a single LR value for each observation without propagating uncertainty",
    "Confusing likelihood ratios with probabilities",
    "Not recognizing that conflicting evidence partially offsets prior updates",
    "Failing to account for compounding uncertainty across multiple uncertain LRs"
  ],
  "metadata": {
    "author": "generator_sequential_updating",
    "reviewed": false,
    "source_inspiration": "original"
  }
}