{
  "id": "MURU-1035",
  "category": "distribution_estimation",
  "difficulty": 3,
  "stem": "A materials science dataset contains 100 observations of tensile strength. The data is believed to come from a mixture of two populations: bulk material (mean \u2248 35.8 MPa, SD \u2248 3.9) and surface-treated material (mean \u2248 89.4 MPa, SD \u2248 11.1). The proportion of bulk material in the sample is uncertain, estimated between 32% and 43%. The observed overall mean is 69.0 MPa with SD = 27.6. Estimate the true population mean of tensile strength, accounting for the uncertainty in the mixing proportion.",
  "uncertainty_type": "model_uncertainty",
  "required_framework": "bayesian_inference",
  "ground_truth": {
    "answer": "Mixture mean = w\u00d735.8 + (1-w)\u00d789.4. As w varies from 0.32 to 0.43, the mixture mean ranges from 66.4 to 72.2. With sampling variability, CI = [61.0, 77.6]. Point estimate at w=0.38: 69.0 MPa.",
    "point_estimate": 69.0,
    "confidence_interval": [
      61.0,
      77.6
    ],
    "ci_level": 0.95
  },
  "solution_steps": [
    "Mixture mean formula: \u03bc_mix = w \u00d7 \u03bc_A + (1-w) \u00d7 \u03bc_B.",
    "At w=0.38: \u03bc_mix = 0.38\u00d735.8 + 0.62\u00d789.4 = 69.0.",
    "At w=0.32: \u03bc_mix = 72.2 (more of surface-treated material).",
    "At w=0.43: \u03bc_mix = 66.4 (more of bulk material).",
    "Mixture SD \u2248 27.6. SE = 27.6/\u221a100 = 2.76.",
    "Combined interval [61.0, 77.6] accounts for both mixing uncertainty and sampling variability."
  ],
  "common_failure_modes": [
    "Using the simple average of the two component means without weighting",
    "Treating the mixing proportion as known instead of uncertain",
    "Ignoring that the overall SD (27.6) is inflated by the between-component variation"
  ],
  "metadata": {
    "author": "generator_mixture_distribution",
    "reviewed": false,
    "source_inspiration": "original"
  }
}