{
  "id": "MURU-2515",
  "category": "conditional_probability_chains",
  "difficulty": 4,
  "stem": "A candidate enters the hiring pipeline. The probability of passing resume screening is between 66% and 83% (uncertain due to evaluator variability). If the previous stage is passed, the probability of passing phone interview is 91%. If the previous stage is passed, the probability of passing onsite interview is 81%. If the previous stage is passed, the probability of passing offer acceptance is 79%. What is the overall probability that the candidate is hired?",
  "uncertainty_type": "parameter_uncertainty",
  "required_framework": "bayesian_inference",
  "ground_truth": {
    "answer": "P(hired) ranges from 0.384 to 0.483 as the resume screening pass rate varies from 66% to 83%. Point estimate: 0.431.",
    "point_estimate": 0.431,
    "confidence_interval": [
      0.384,
      0.483
    ],
    "ci_level": 0.9
  },
  "solution_steps": [
    "The candidate must pass all 4 stages sequentially: P(success) = P(stage 1)\u00d7P(stage 2)\u00d7P(stage 3)\u00d7P(stage 4).",
    "At mid-range: P(success) = 0.74 \u00d7 0.91 \u00d7 0.81 \u00d7 0.79 = 0.431.",
    "At lower bound: P(success) = 0.66 \u00d7 0.91 \u00d7 0.81 \u00d7 0.79 = 0.384.",
    "At upper bound: P(success) = 0.83 \u00d7 0.91 \u00d7 0.81 \u00d7 0.79 = 0.483.",
    "The uncertainty in the resume screening stage creates a 9.9 percentage point range in the overall success probability."
  ],
  "common_failure_modes": [
    "Adding probabilities instead of multiplying for sequential stages",
    "Using a single value for the resume screening rate without acknowledging uncertainty",
    "Not recognizing that uncertainty at one stage propagates through all subsequent stages"
  ],
  "metadata": {
    "author": "generator_pipeline",
    "reviewed": false,
    "source_inspiration": "original"
  }
}