{
  "id": "MURU-2689",
  "category": "bayesian_updating",
  "difficulty": 3,
  "stem": "In a environmental monitoring scenario, a researcher begins with a prior probability of 22% that pollution exceeds safe limits, based on sensor readings. After sampling period 1, contradicting evidence arrives with a likelihood ratio estimated between 0.25 and 0.39. After sampling period 2, supporting evidence arrives with a likelihood ratio estimated between 2.71 and 3.56. What is the posterior probability that pollution exceeds safe limits after all 2 observations, accounting for the uncertainty in each likelihood ratio?",
  "uncertainty_type": "parameter_uncertainty",
  "required_framework": "bayesian_inference",
  "ground_truth": {
    "answer": "After 2 sequential Bayesian updates, P(pollution exceeds safe limits) ranges from 0.16 to 0.281. Point estimate: 0.22.",
    "point_estimate": 0.22,
    "confidence_interval": [
      0.16,
      0.281
    ],
    "ci_level": 0.9
  },
  "solution_steps": [
    "Start with prior odds = 0.22/0.78 = 0.282.",
    "Update 1: multiply odds by LR \u2208 [0.25, 0.39] (mid: 0.32, contradicting evidence).",
    "Update 2: multiply odds by LR \u2208 [2.71, 3.56] (mid: 3.13, supporting evidence).",
    "Convert final odds back to probability: P = odds/(1+odds). Range: [0.16, 0.281], point estimate: 0.22."
  ],
  "common_failure_modes": [
    "Treating each update independently instead of applying them sequentially to the running posterior",
    "Using a single LR value for each observation without propagating uncertainty",
    "Confusing likelihood ratios with probabilities"
  ],
  "metadata": {
    "author": "generator_sequential_updating",
    "reviewed": false,
    "source_inspiration": "original"
  }
}